setup.py
vecnet/__init__.py
vecnet.winhpc.egg-info/PKG-INFO
vecnet.winhpc.egg-info/SOURCES.txt
vecnet.winhpc.egg-info/dependency_links.txt
vecnet.winhpc.egg-info/requires.txt
vecnet.winhpc.egg-info/top_level.txt
vecnet/winhpc/__init__.py
vecnet/winhpc/submit.py
vecnet/winhpc/webapi.py