Metadata-Version: 1.1
Name: vecnet.winhpc
Version: 0.7.0
Summary: Python interface for Windows HPC Server REST API
Home-page: https://github.com/vecnet/vecnet.winhpc
Author: Alexander Vyushkov
Author-email: alex.vyushkov@gmail.com
License: MPL 2.0
Keywords: winhpc hpc scheduler windows webapi rest api
Platform: UNKNOWN
Classifier: Development Status :: 3 - Alpha
Classifier: License :: OSI Approved :: Mozilla Public License 2.0 (MPL 2.0)
Classifier: Intended Audience :: Developers
Classifier: Operating System :: OS Independent
Classifier: Programming Language :: Python
Classifier: Programming Language :: Python :: 2
Classifier: Programming Language :: Python :: 2.7
Classifier: Topic :: Software Development :: Libraries :: Python Modules
